setup.py
flask_srd/__init__.py
flask_srd/consul.py
flask_srd/consul_dns.py
flask_srd/decorators.py
flask_srd/exceptions.py
flask_srd/service.py
flask_srd.egg-info/PKG-INFO
flask_srd.egg-info/SOURCES.txt
flask_srd.egg-info/dependency_links.txt
flask_srd.egg-info/not-zip-safe
flask_srd.egg-info/requires.txt
flask_srd.egg-info/top_level.txt