Metadata-Version: 1.1
Name: flask-srd
Version: 0.0.1
Summary: flask extension that provides service registry and discovery functionality
Home-page: http://github.com/megachweng/flask-srd
Author: megachweng
Author-email: megachweng@gmail.com
License: MIT
Platform: any
Classifier: Development Status :: 4 - Beta
Classifier: Environment :: Web Environment
Classifier: Intended Audience :: Developers
Classifier: License :: OSI Approved :: MIT License
Classifier: Operating System :: OS Independent
Classifier: Programming Language :: Python :: 3
Classifier: Topic :: Internet :: WWW/HTTP :: Dynamic Content
Classifier: Topic :: Software Development :: Libraries :: Python Modules
